<annotation>
	<folder></folder>
	<filename>levle2_74_jpg.rf.c1df92c30de6d0a200493a16657dccc4.jpg</filename>
	<path>levle2_74_jpg.rf.c1df92c30de6d0a200493a16657dccc4.jpg</path>
	<source>
		<database>roboflow.ai</database>
	</source>
	<size>
		<width>376</width>
		<height>416</height>
		<depth>3</depth>
	</size>
	<segmented>0</segmented>
	<object>
		<name>dark spot</name>
		<pose>Unspecified</pose>
		<truncated>0</truncated>
		<difficult>0</difficult>
		<occluded>0</occluded>
		<bndbox>
			<xmin>300</xmin>
			<xmax>315</xmax>
			<ymin>134</ymin>
			<ymax>165</ymax>
		</bndbox>
	</object>
	<object>
		<name>dark spot</name>
		<pose>Unspecified</pose>
		<truncated>0</truncated>
		<difficult>0</difficult>
		<occluded>0</occluded>
		<bndbox>
			<xmin>294</xmin>
			<xmax>328</xmax>
			<ymin>180</ymin>
			<ymax>205</ymax>
		</bndbox>
	</object>
	<object>
		<name>blackheads</name>
		<pose>Unspecified</pose>
		<truncated>0</truncated>
		<difficult>0</difficult>
		<occluded>0</occluded>
		<bndbox>
			<xmin>186</xmin>
			<xmax>198</xmax>
			<ymin>282</ymin>
			<ymax>293</ymax>
		</bndbox>
	</object>
	<object>
		<name>dark spot</name>
		<pose>Unspecified</pose>
		<truncated>0</truncated>
		<difficult>0</difficult>
		<occluded>0</occluded>
		<bndbox>
			<xmin>249</xmin>
			<xmax>267</xmax>
			<ymin>280</ymin>
			<ymax>305</ymax>
		</bndbox>
	</object>
	<object>
		<name>dark spot</name>
		<pose>Unspecified</pose>
		<truncated>0</truncated>
		<difficult>0</difficult>
		<occluded>0</occluded>
		<bndbox>
			<xmin>152</xmin>
			<xmax>168</xmax>
			<ymin>290</ymin>
			<ymax>317</ymax>
		</bndbox>
	</object>
	<object>
		<name>dark spot</name>
		<pose>Unspecified</pose>
		<truncated>0</truncated>
		<difficult>0</difficult>
		<occluded>0</occluded>
		<bndbox>
			<xmin>261</xmin>
			<xmax>286</xmax>
			<ymin>337</ymin>
			<ymax>358</ymax>
		</bndbox>
	</object>
	<object>
		<name>dark spot</name>
		<pose>Unspecified</pose>
		<truncated>0</truncated>
		<difficult>0</difficult>
		<occluded>0</occluded>
		<bndbox>
			<xmin>203</xmin>
			<xmax>231</xmax>
			<ymin>77</ymin>
			<ymax>98</ymax>
		</bndbox>
	</object>
	<object>
		<name>dark spot</name>
		<pose>Unspecified</pose>
		<truncated>0</truncated>
		<difficult>0</difficult>
		<occluded>0</occluded>
		<bndbox>
			<xmin>297</xmin>
			<xmax>313</xmax>
			<ymin>102</ymin>
			<ymax>133</ymax>
		</bndbox>
	</object>
</annotation>
