<annotation>
	<folder></folder>
	<filename>levle0_291_jpg.rf.0fe8c9e0bde06c8a688d9f6f045095b6.jpg</filename>
	<path>levle0_291_jpg.rf.0fe8c9e0bde06c8a688d9f6f045095b6.jpg</path>
	<source>
		<database>roboflow.ai</database>
	</source>
	<size>
		<width>376</width>
		<height>416</height>
		<depth>3</depth>
	</size>
	<segmented>0</segmented>
	<object>
		<name>whiteheads</name>
		<pose>Unspecified</pose>
		<truncated>0</truncated>
		<difficult>0</difficult>
		<occluded>0</occluded>
		<bndbox>
			<xmin>163</xmin>
			<xmax>179</xmax>
			<ymin>220</ymin>
			<ymax>237</ymax>
		</bndbox>
	</object>
	<object>
		<name>whiteheads</name>
		<pose>Unspecified</pose>
		<truncated>0</truncated>
		<difficult>0</difficult>
		<occluded>0</occluded>
		<bndbox>
			<xmin>163</xmin>
			<xmax>178</xmax>
			<ymin>252</ymin>
			<ymax>265</ymax>
		</bndbox>
	</object>
	<object>
		<name>dark spot</name>
		<pose>Unspecified</pose>
		<truncated>0</truncated>
		<difficult>0</difficult>
		<occluded>0</occluded>
		<bndbox>
			<xmin>181</xmin>
			<xmax>195</xmax>
			<ymin>270</ymin>
			<ymax>285</ymax>
		</bndbox>
	</object>
	<object>
		<name>whiteheads</name>
		<pose>Unspecified</pose>
		<truncated>0</truncated>
		<difficult>0</difficult>
		<occluded>0</occluded>
		<bndbox>
			<xmin>139</xmin>
			<xmax>154</xmax>
			<ymin>279</ymin>
			<ymax>291</ymax>
		</bndbox>
	</object>
	<object>
		<name>dark spot</name>
		<pose>Unspecified</pose>
		<truncated>0</truncated>
		<difficult>0</difficult>
		<occluded>0</occluded>
		<bndbox>
			<xmin>149</xmin>
			<xmax>184</xmax>
			<ymin>298</ymin>
			<ymax>325</ymax>
		</bndbox>
	</object>
</annotation>
